{
 "labels": [
  "Hikaru Nakamura",
  "Daniel Naroditsky",
  "Olexandr Bortnyk",
  "Andrew Tang",
  "Jose Martinez Alcantara",
  "Nihal Sarin",
  "Le Tuan Minh",
  "Ediz Gurel",
  "Yoseph Theolifus Taher",
  "Yagiz Kaan Erdogmus",
  "Renato Terry",
  "Magnus Carlsen",
  "Arjun Erigaisi",
  "David Paravyan (*)",
  "Sergei Zhigalko",
  "Christopher Yoo",
  "Eric Hansen",
  "Emin Ohanyan",
  "Maxime Vachier-Lagrave",
  "Pranav Venkatesh",
  "Matthias Bluebaum",
  "Andy Woodward",
  "Alan Pichot",
  "Nikolas Theodorou (*)",
  "Rauf Mamedov",
  "Rasmus Svane",
  "Samuel Sevian",
  "Benjamin Bok",
  "Federico Perez Ponsa",
  "Jorden van Foreest",
  "Kacper Drozdowski",
  "Sunilduth Lyna Narayanan",
  "Aram Hakobyan (B)",
  "Mykola Bortnyk",
  "Raunak Sadhwani",
  "Pranesh Munirethinam",
  "Frederik Svane",
  "Anish Giri",
  "Marcos Lianes",
  "Hans Niemann (M)",
  "Alireza Firouzja"
 ],
 "datasets": [
  {
   "label": "Gold",
   "data": [
    29,
    23,
    9,
    4,
    3,
    2,
    1,
    1,
    1,
    1,
    0,
    0,
    0,
    0,
    0,
    0,
    0,
    0,
    0,
    0,
    0,
    0,
    0,
    0,
    0,
    0,
    0,
    0,
    0,
    0,
    0,
    0,
    0,
    0,
    0,
    0,
    0,
    0,
    0,
    0,
    0
   ],
   "backgroundColor": "rgba(212, 175, 55, 0.5)",
   "borderColor": "rgba(198, 147, 10, 1.0)",
   "borderWidth": 1
  },
  {
   "label": "Silver",
   "data": [
    11,
    21,
    14,
    7,
    9,
    1,
    2,
    2,
    1,
    0,
    2,
    1,
    1,
    1,
    1,
    0,
    0,
    0,
    0,
    0,
    0,
    0,
    0,
    0,
    0,
    0,
    0,
    0,
    0,
    0,
    0,
    0,
    0,
    0,
    0,
    0,
    0,
    0,
    0,
    0,
    0
   ],
   "backgroundColor": "rgba(172, 172, 172, 0.5)",
   "borderColor": "rgba(132, 132, 130, 1.0)",
   "borderWidth": 1
  },
  {
   "label": "Bronze",
   "data": [
    2,
    10,
    11,
    13,
    16,
    1,
    4,
    0,
    6,
    1,
    3,
    1,
    1,
    0,
    0,
    1,
    1,
    1,
    1,
    1,
    0,
    0,
    0,
    0,
    0,
    0,
    0,
    0,
    0,
    0,
    0,
    0,
    0,
    0,
    0,
    0,
    0,
    0,
    0,
    0,
    0
   ],
   "backgroundColor": "rgba(205, 127, 50, 0.5)",
   "borderColor": "rgba(165, 113, 100, 1.0)",
   "borderWidth": 1
  },
  {
   "label": "Fourth",
   "data": [
    0,
    4,
    15,
    3,
    6,
    4,
    5,
    0,
    4,
    0,
    10,
    0,
    0,
    2,
    0,
    3,
    1,
    0,
    0,
    0,
    3,
    3,
    3,
    2,
    1,
    1,
    1,
    1,
    1,
    1,
    0,
    0,
    0,
    0,
    0,
    0,
    0,
    0,
    0,
    0,
    0
   ],
   "backgroundColor": "rgba(31, 117, 254, 0.2)",
   "borderColor": "rgba(0, 24, 168, 0.5)",
   "borderWidth": 1
  },
  {
   "label": "Fifth",
   "data": [
    0,
    0,
    8,
    2,
    4,
    3,
    8,
    2,
    5,
    0,
    5,
    1,
    0,
    3,
    0,
    2,
    2,
    5,
    1,
    0,
    2,
    2,
    1,
    1,
    1,
    0,
    0,
    0,
    0,
    0,
    2,
    2,
    2,
    2,
    2,
    1,
    1,
    1,
    1,
    1,
    1
   ],
   "backgroundColor": "rgba(0, 173, 131, 0.2)",
   "borderColor": "rgba(1, 163, 104, 0.5)",
   "borderWidth": 1
  }
 ]
}