{
 "labels": [
  "Olexandr Bortnyk",
  "Nihal Sarin",
  "Jose Martinez Alcantara",
  "Daniel Naroditsky",
  "Alireza Firouzja",
  "Le Tuan Minh",
  "David Paravyan",
  "Magnus Carlsen",
  "Daniil Dubov",
  "Vladimir Fedoseev",
  "GM Hooligan64",
  "Andrew Tang",
  "Dmitry Andreikin",
  "GM Arka50",
  "Shant Sargsyan",
  "Sanan Sjugirov",
  "Alexey Sarana",
  "Andy Woodward",
  "Vincent Keymer",
  "Rauf Mamedov",
  "Jeffery Xiong",
  "Vladislav Artemiev",
  "GM Grey_parrot",
  "Mahammad Muradli",
  "Brandon Jacobson",
  "GM Watneg",
  "Arjun Erigaisi",
  "Mukhiddin Madaminov",
  "Shakhriyar Mamedyarov",
  "Reza Mahdavi",
  "Gata Kamsky",
  "Jakhongir Vakhidov",
  "Zohiiidd_10",
  "GM retired93",
  "Akshat Chandra",
  "Sergei Zhigalko",
  "Zhamsaran Tsydypov",
  "Aravindh Chithambaram",
  "Renato Terry",
  "Dincer Tasdogen",
  "Yoseph Theolifus Taher",
  "Guha Mitrabha",
  "Aram Hakobyan",
  "Volodar Murzin",
  "Hans Niemann",
  "Matvey Galchenko",
  "Masoud Mosadeghpour",
  "Zaven Andriasian",
  "Javokhir Sindarov",
  "Vladislav Kovalev",
  "Matthias Bluebaum",
  "Emin Ohanyan",
  "Leon Livaic (X)",
  "Sunilduth Lyna Narayanan",
  "Dmitry Tsoi",
  "Shamsiddin Vokhidov",
  "FM Mirakel05",
  "Vladimir Zakhartsov",
  "Cresswell",
  "Khumoyun Begmuratov",
  "Vahap Sanal",
  "Eray Kilic",
  "Mykola Bortnyk",
  "Vugar Rasulov",
  "Maksim Chigaev",
  "Mustafa Yilmaz",
  "handofprince",
  "GM Eyesless18",
  "Saveliy Golubov (X)",
  "Thomas Beerdsen",
  "Amin Tabatabaei",
  "IM ZodabwitsaIM",
  "Raunak Sadhwani",
  "Timur Gareyev",
  "Rasmus Svane",
  "Savva Vetokhin",
  "Samir Sahidi",
  "Eric Hansen",
  "Vladimir Seliverstov",
  "Vasif Durarbayli",
  "Anish Giri",
  "Seyed Khalil Mousavi",
  "Elham Amar-Abdrlauf",
  "DuXiaosu",
  "Saparmyrat Atabayev",
  "Haik Martirosyan",
  "Abdulla Gadimbayli",
  "Mamikon Gharibyan",
  "GM Twelvedigits",
  "Abdimalik Abdisalimov",
  "Paulius Pultinevicius",
  "LyinTed",
  "Khazar Babazada",
  "niekeZpieczny91",
  "Janak Awatramani",
  "Vincent Rothuis",
  "Nodirbek Abdusattorov",
  "Jose Carlos Ibarra",
  "Rameshbabu Praggnanandhaa",
  "GM Chamaeleon3",
  "Pranav Venkatesh",
  "yesaiedo",
  "Alex Astaneh"
 ],
 "datasets": [
  {
   "label": "Gold",
   "data": [
    8,
    4,
    4,
    3,
    3,
    2,
    2,
    2,
    2,
    2,
    2,
    1,
    1,
    1,
    1,
    1,
    1,
    1,
    1,
    0,
    0,
    0,
    0,
    0,
    0,
    0,
    0,
    0,
    0,
    0,
    0,
    0,
    0,
    0,
    0,
    0,
    0,
    0,
    0,
    0,
    0,
    0,
    0,
    0,
    0,
    0,
    0,
    0,
    0,
    0,
    0,
    0,
    0,
    0,
    0,
    0,
    0,
    0,
    0,
    0,
    0,
    0,
    0,
    0,
    0,
    0,
    0,
    0,
    0,
    0,
    0,
    0,
    0,
    0,
    0,
    0,
    0,
    0,
    0,
    0,
    0,
    0,
    0,
    0,
    0,
    0,
    0,
    0,
    0,
    0,
    0,
    0,
    0,
    0,
    0,
    0,
    0,
    0,
    0,
    0,
    0,
    0,
    0
   ],
   "backgroundColor": "rgba(212, 175, 55, 0.5)",
   "borderColor": "rgba(198, 147, 10, 1.0)",
   "borderWidth": 1
  },
  {
   "label": "Silver",
   "data": [
    5,
    2,
    2,
    4,
    1,
    3,
    2,
    2,
    1,
    0,
    0,
    1,
    0,
    0,
    0,
    0,
    0,
    0,
    0,
    2,
    2,
    2,
    1,
    1,
    1,
    1,
    1,
    1,
    1,
    1,
    1,
    1,
    1,
    1,
    1,
    0,
    0,
    0,
    0,
    0,
    0,
    0,
    0,
    0,
    0,
    0,
    0,
    0,
    0,
    0,
    0,
    0,
    0,
    0,
    0,
    0,
    0,
    0,
    0,
    0,
    0,
    0,
    0,
    0,
    0,
    0,
    0,
    0,
    0,
    0,
    0,
    0,
    0,
    0,
    0,
    0,
    0,
    0,
    0,
    0,
    0,
    0,
    0,
    0,
    0,
    0,
    0,
    0,
    0,
    0,
    0,
    0,
    0,
    0,
    0,
    0,
    0,
    0,
    0,
    0,
    0,
    0,
    0
   ],
   "backgroundColor": "rgba(172, 172, 172, 0.5)",
   "borderColor": "rgba(132, 132, 130, 1.0)",
   "borderWidth": 1
  },
  {
   "label": "Bronze",
   "data": [
    8,
    3,
    2,
    4,
    1,
    1,
    1,
    0,
    0,
    1,
    0,
    0,
    4,
    2,
    0,
    0,
    0,
    0,
    0,
    0,
    0,
    0,
    1,
    0,
    0,
    0,
    0,
    0,
    0,
    0,
    0,
    0,
    0,
    0,
    0,
    3,
    1,
    1,
    1,
    1,
    1,
    1,
    1,
    1,
    1,
    1,
    1,
    0,
    0,
    0,
    0,
    0,
    0,
    0,
    0,
    0,
    0,
    0,
    0,
    0,
    0,
    0,
    0,
    0,
    0,
    0,
    0,
    0,
    0,
    0,
    0,
    0,
    0,
    0,
    0,
    0,
    0,
    0,
    0,
    0,
    0,
    0,
    0,
    0,
    0,
    0,
    0,
    0,
    0,
    0,
    0,
    0,
    0,
    0,
    0,
    0,
    0,
    0,
    0,
    0,
    0,
    0,
    0
   ],
   "backgroundColor": "rgba(205, 127, 50, 0.5)",
   "borderColor": "rgba(165, 113, 100, 1.0)",
   "borderWidth": 1
  },
  {
   "label": "Fourth",
   "data": [
    2,
    0,
    3,
    0,
    0,
    3,
    1,
    0,
    0,
    0,
    1,
    0,
    0,
    0,
    2,
    0,
    0,
    0,
    0,
    1,
    1,
    0,
    0,
    2,
    1,
    0,
    0,
    0,
    0,
    0,
    0,
    0,
    0,
    0,
    0,
    1,
    2,
    2,
    1,
    1,
    1,
    0,
    0,
    0,
    0,
    0,
    0,
    3,
    2,
    2,
    1,
    1,
    1,
    1,
    1,
    1,
    1,
    1,
    1,
    1,
    0,
    0,
    0,
    0,
    0,
    0,
    0,
    0,
    0,
    0,
    0,
    0,
    0,
    0,
    0,
    0,
    0,
    0,
    0,
    0,
    0,
    0,
    0,
    0,
    0,
    0,
    0,
    0,
    0,
    0,
    0,
    0,
    0,
    0,
    0,
    0,
    0,
    0,
    0,
    0,
    0,
    0,
    0
   ],
   "backgroundColor": "rgba(31, 117, 254, 0.2)",
   "borderColor": "rgba(0, 24, 168, 0.5)",
   "borderWidth": 1
  },
  {
   "label": "Fifth",
   "data": [
    0,
    0,
    1,
    0,
    0,
    3,
    1,
    0,
    0,
    0,
    1,
    1,
    2,
    0,
    0,
    1,
    0,
    0,
    0,
    0,
    0,
    0,
    0,
    2,
    0,
    0,
    0,
    0,
    0,
    0,
    0,
    0,
    0,
    0,
    0,
    0,
    2,
    0,
    4,
    1,
    0,
    1,
    0,
    0,
    0,
    0,
    0,
    2,
    3,
    0,
    1,
    1,
    0,
    0,
    0,
    0,
    0,
    0,
    0,
    0,
    2,
    1,
    1,
    1,
    1,
    1,
    1,
    1,
    1,
    1,
    1,
    1,
    1,
    1,
    0,
    0,
    0,
    0,
    0,
    0,
    0,
    0,
    0,
    0,
    0,
    0,
    0,
    0,
    0,
    0,
    0,
    0,
    0,
    0,
    0,
    0,
    0,
    0,
    0,
    0,
    0,
    0,
    0
   ],
   "backgroundColor": "rgba(0, 173, 131, 0.2)",
   "borderColor": "rgba(1, 163, 104, 0.5)",
   "borderWidth": 1
  },
  {
   "label": "Sixth",
   "data": [
    1,
    0,
    0,
    1,
    0,
    0,
    0,
    0,
    0,
    0,
    0,
    0,
    1,
    1,
    0,
    1,
    1,
    0,
    0,
    0,
    0,
    1,
    0,
    1,
    1,
    2,
    1,
    1,
    1,
    0,
    0,
    0,
    0,
    0,
    0,
    1,
    0,
    1,
    2,
    0,
    0,
    1,
    1,
    1,
    0,
    0,
    0,
    0,
    0,
    0,
    3,
    2,
    2,
    1,
    0,
    0,
    0,
    0,
    0,
    0,
    0,
    1,
    1,
    0,
    0,
    0,
    0,
    0,
    0,
    0,
    0,
    0,
    0,
    0,
    2,
    1,
    1,
    1,
    1,
    1,
    1,
    1,
    1,
    1,
    0,
    0,
    0,
    0,
    0,
    0,
    0,
    0,
    0,
    0,
    0,
    0,
    0,
    0,
    0,
    0,
    0,
    0,
    0
   ],
   "backgroundColor": "rgba(255, 0, 0, 0.1)",
   "borderColor": "rgba(255, 0, 0, 0.5)",
   "borderWidth": 1
  },
  {
   "label": "Seventh",
   "data": [
    1,
    0,
    0,
    0,
    0,
    2,
    3,
    0,
    2,
    2,
    0,
    1,
    1,
    0,
    0,
    1,
    1,
    0,
    0,
    0,
    0,
    1,
    0,
    1,
    1,
    2,
    0,
    0,
    0,
    0,
    0,
    0,
    0,
    0,
    0,
    1,
    1,
    1,
    1,
    0,
    0,
    1,
    1,
    0,
    0,
    0,
    0,
    0,
    0,
    0,
    0,
    0,
    0,
    0,
    1,
    0,
    0,
    0,
    0,
    0,
    0,
    2,
    1,
    1,
    0,
    0,
    0,
    0,
    0,
    0,
    0,
    0,
    0,
    0,
    2,
    0,
    0,
    0,
    0,
    0,
    0,
    0,
    0,
    0,
    1,
    1,
    1,
    1,
    1,
    1,
    1,
    1,
    1,
    1,
    0,
    0,
    0,
    0,
    0,
    0,
    0,
    0,
    0
   ],
   "backgroundColor": "rgba(191, 0, 255, 0.2)",
   "borderColor": "rgba(128, 0, 128, 0.5)",
   "borderWidth": 1
  },
  {
   "label": "Eighth",
   "data": [
    2,
    0,
    0,
    0,
    0,
    0,
    1,
    0,
    1,
    1,
    0,
    0,
    3,
    1,
    0,
    2,
    0,
    0,
    0,
    1,
    0,
    0,
    0,
    2,
    0,
    0,
    0,
    0,
    0,
    3,
    0,
    0,
    0,
    0,
    0,
    3,
    0,
    1,
    1,
    0,
    1,
    1,
    0,
    0,
    1,
    0,
    0,
    0,
    0,
    0,
    0,
    1,
    0,
    0,
    0,
    0,
    0,
    0,
    0,
    0,
    0,
    1,
    1,
    0,
    2,
    1,
    0,
    0,
    0,
    0,
    0,
    0,
    0,
    0,
    0,
    1,
    0,
    0,
    0,
    0,
    0,
    0,
    0,
    0,
    1,
    0,
    0,
    0,
    0,
    0,
    0,
    0,
    0,
    0,
    1,
    1,
    1,
    1,
    1,
    1,
    1,
    1,
    1
   ],
   "backgroundColor": "rgba(136, 176, 75, 0.2)",
   "borderColor": "rgba(0, 148, 115, 0.5)",
   "borderWidth": 1
  }
 ]
}